steam_playtime.py
steam_playtime_to_sqlite-0.2.1.dist-info/METADATA
steam_playtime_to_sqlite-0.2.1.dist-info/WHEEL
steam_playtime_to_sqlite-0.2.1.dist-info/entry_points.txt
steam_playtime_to_sqlite-0.2.1.dist-info/top_level.txt
steam_playtime_to_sqlite-0.2.1.dist-info/RECORD
