Metadata-Version: 2.4
Name: steam-playtime-to-sqlite
Version: 0.2.1
Summary: Track and analyze Steam playtime statistics
Author-email: Manuel Grabowski <steam@manuelgrabowski.de>
License-Expression: GPL-3.0-only
Project-URL: Homepage, https://github.com/manuelgrabowski/steam-playtime-to-sqlite
Project-URL: Bug Tracker, https://github.com/manuelgrabowski/steam-playtime-to-sqlite/issues
Classifier: Environment :: Console
Classifier: Topic :: Games/Entertainment
Classifier: Topic :: Utilities
Requires-Python: >=3.13
Requires-Dist: requests>=2.25.0
Provides-Extra: dev
Requires-Dist: ruff==0.4.4; extra == "dev"
Requires-Dist: mypy==1.15.0; extra == "dev"
